setup.cfg
setup.py
drf_true_datetime/__init__.py
drf_true_datetime/fields.py
drf_true_datetime.egg-info/PKG-INFO
drf_true_datetime.egg-info/SOURCES.txt
drf_true_datetime.egg-info/dependency_links.txt
drf_true_datetime.egg-info/top_level.txt