Metadata-Version: 1.1
Name: drf-true-datetime
Version: 0.1.0
Summary: Custom date time field for DRF to fix bad client time
Home-page: https://github.com/hypertrack/drf-true-datetime
Author: HyperTrack
Author-email: devops@hypertrack.io
License: MIT
Download-URL: https://github.com/hypertrack/drf-true-datetime/tarball/0.1
Keywords: drf,django,datetime
Platform: UNKNOWN
